{
  "metadata" : {
    "identifier" : "https://nhattruyenz.com/truyen-tranh/bat-dau-voi-100-trieu-mang",
    "title" : "Bắt Đầu Với 100 Triệu Mạng",
    "subtitle" : null,
    "author" : null,
    "narrator" : null,
    "language" : "vi",
    "description" : null,
    "publisher" : "N/A",
    "subject" : null,
    "modified" : null,
    "published" : "2023-05-01",
    "duration" : 0,
    "abridged" : false,
    "conformsTo" : "https://readium.org/webpub-manifest/profiles/divina",
    "numberOfPages" : 27,
    "readingProgression" : "ttb",
    "belongsTo" : null,
    "presentation" : {
      "fit" : "width",
      "overflow" : "scrolled",
      "continuous" : true
    },
    "@type" : null,
    "schema:license" : null
  },
  "links" : [ {
    "rel" : "self",
    "href" : "https://raw.githubusercontent.com/thuvienonline40/book_storage_collection/main/comic_manifest.json",
    "type" : "application/divina+json"
  } ],
  "readingOrder" : [ {
    "href" : "https://bitbucket.org/wp-tsvhcomic29/comic_storage_two19/raw/master/IMAGE/IMAGE_0a47bd719caa874504c64c192d6dae91_f451f913d5303770df71e77caa48c886_6946886ce37c047b4feb50446bced0e7.jpg",
    "type" : "image/jpeg",
    "bitrate" : 0,
    "duration" : 0,
    "title" : null,
    "properties" : null,
    "alternate" : [ {
      "href" : "https://img.abctruyen.xyz/uploads/19268/chuong-10/1.jpg",
      "type" : "image/jpeg",
      "bitrate" : 0,
      "duration" : 0,
      "title" : null,
      "properties" : null,
      "alternate" : null
    }, {
      "href" : "https://i2.wp.com/img.abctruyen.xyz/uploads/19268/chuong-10/1.jpg",
      "type" : "image/jpeg",
      "bitrate" : 0,
      "duration" : 0,
      "title" : null,
      "properties" : null,
      "alternate" : null
    } ]
  }, {
    "href" : "https://bitbucket.org/wp-tsvhcomic29/comic_storage_two19/raw/master/IMAGE/IMAGE_0a47bd719caa874504c64c192d6dae91_f451f913d5303770df71e77caa48c886_b6b56cc1a0e1a9ab6dc0a16922a03d71.jpg",
    "type" : "image/jpeg",
    "bitrate" : 0,
    "duration" : 0,
    "title" : null,
    "properties" : null,
    "alternate" : [ {
      "href" : "https://img.abctruyen.xyz/uploads/19268/chuong-10/2.jpg",
      "type" : "image/jpeg",
      "bitrate" : 0,
      "duration" : 0,
      "title" : null,
      "properties" : null,
      "alternate" : null
    }, {
      "href" : "https://i2.wp.com/img.abctruyen.xyz/uploads/19268/chuong-10/2.jpg",
      "type" : "image/jpeg",
      "bitrate" : 0,
      "duration" : 0,
      "title" : null,
      "properties" : null,
      "alternate" : null
    } ]
  }, {
    "href" : "https://bitbucket.org/wp-tsvhcomic29/comic_storage_two19/raw/master/IMAGE/IMAGE_0a47bd719caa874504c64c192d6dae91_f451f913d5303770df71e77caa48c886_f654e5f8f4a9c55d5d0daa92278a7b84.jpg",
    "type" : "image/jpeg",
    "bitrate" : 0,
    "duration" : 0,
    "title" : null,
    "properties" : null,
    "alternate" : [ {
      "href" : "https://img.abctruyen.xyz/uploads/19268/chuong-10/3.jpg",
      "type" : "image/jpeg",
      "bitrate" : 0,
      "duration" : 0,
      "title" : null,
      "properties" : null,
      "alternate" : null
    }, {
      "href" : "https://i2.wp.com/img.abctruyen.xyz/uploads/19268/chuong-10/3.jpg",
      "type" : "image/jpeg",
      "bitrate" : 0,
      "duration" : 0,
      "title" : null,
      "properties" : null,
      "alternate" : null
    } ]
  }, {
    "href" : "https://bitbucket.org/wp-tsvhcomic29/comic_storage_two19/raw/master/IMAGE/IMAGE_0a47bd719caa874504c64c192d6dae91_f451f913d5303770df71e77caa48c886_16faaac6769d71b8ed0cc38fc6a8f73f.jpg",
    "type" : "image/jpeg",
    "bitrate" : 0,
    "duration" : 0,
    "title" : null,
    "properties" : null,
    "alternate" : [ {
      "href" : "https://img.abctruyen.xyz/uploads/19268/chuong-10/4.jpg",
      "type" : "image/jpeg",
      "bitrate" : 0,
      "duration" : 0,
      "title" : null,
      "properties" : null,
      "alternate" : null
    }, {
      "href" : "https://i2.wp.com/img.abctruyen.xyz/uploads/19268/chuong-10/4.jpg",
      "type" : "image/jpeg",
      "bitrate" : 0,
      "duration" : 0,
      "title" : null,
      "properties" : null,
      "alternate" : null
    } ]
  }, {
    "href" : "https://bitbucket.org/wp-tsvhcomic29/comic_storage_two19/raw/master/IMAGE/IMAGE_0a47bd719caa874504c64c192d6dae91_f451f913d5303770df71e77caa48c886_ac26af2a6380104ab9828d6352ab45a2.jpg",
    "type" : "image/jpeg",
    "bitrate" : 0,
    "duration" : 0,
    "title" : null,
    "properties" : null,
    "alternate" : [ {
      "href" : "https://img.abctruyen.xyz/uploads/19268/chuong-10/5.jpg",
      "type" : "image/jpeg",
      "bitrate" : 0,
      "duration" : 0,
      "title" : null,
      "properties" : null,
      "alternate" : null
    }, {
      "href" : "https://i2.wp.com/img.abctruyen.xyz/uploads/19268/chuong-10/5.jpg",
      "type" : "image/jpeg",
      "bitrate" : 0,
      "duration" : 0,
      "title" : null,
      "properties" : null,
      "alternate" : null
    } ]
  }, {
    "href" : "https://bitbucket.org/wp-tsvhcomic29/comic_storage_two19/raw/master/IMAGE/IMAGE_0a47bd719caa874504c64c192d6dae91_f451f913d5303770df71e77caa48c886_79cb50b49c5bd86cde9d1dcba2ec01f7.jpg",
    "type" : "image/jpeg",
    "bitrate" : 0,
    "duration" : 0,
    "title" : null,
    "properties" : null,
    "alternate" : [ {
      "href" : "https://img.abctruyen.xyz/uploads/19268/chuong-10/6.jpg",
      "type" : "image/jpeg",
      "bitrate" : 0,
      "duration" : 0,
      "title" : null,
      "properties" : null,
      "alternate" : null
    }, {
      "href" : "https://i2.wp.com/img.abctruyen.xyz/uploads/19268/chuong-10/6.jpg",
      "type" : "image/jpeg",
      "bitrate" : 0,
      "duration" : 0,
      "title" : null,
      "properties" : null,
      "alternate" : null
    } ]
  }, {
    "href" : "https://bitbucket.org/wp-tsvhcomic29/comic_storage_two19/raw/master/IMAGE/IMAGE_0a47bd719caa874504c64c192d6dae91_f451f913d5303770df71e77caa48c886_f9ae542cd6a027eadf147b8286459ede.jpg",
    "type" : "image/jpeg",
    "bitrate" : 0,
    "duration" : 0,
    "title" : null,
    "properties" : null,
    "alternate" : [ {
      "href" : "https://img.abctruyen.xyz/uploads/19268/chuong-10/7.jpg",
      "type" : "image/jpeg",
      "bitrate" : 0,
      "duration" : 0,
      "title" : null,
      "properties" : null,
      "alternate" : null
    }, {
      "href" : "https://i2.wp.com/img.abctruyen.xyz/uploads/19268/chuong-10/7.jpg",
      "type" : "image/jpeg",
      "bitrate" : 0,
      "duration" : 0,
      "title" : null,
      "properties" : null,
      "alternate" : null
    } ]
  }, {
    "href" : "https://bitbucket.org/wp-tsvhcomic29/comic_storage_two19/raw/master/IMAGE/IMAGE_0a47bd719caa874504c64c192d6dae91_f451f913d5303770df71e77caa48c886_8d858cb10fcfc6aa7bef06cfd7bcccb1.jpg",
    "type" : "image/jpeg",
    "bitrate" : 0,
    "duration" : 0,
    "title" : null,
    "properties" : null,
    "alternate" : [ {
      "href" : "https://img.abctruyen.xyz/uploads/19268/chuong-10/8.jpg",
      "type" : "image/jpeg",
      "bitrate" : 0,
      "duration" : 0,
      "title" : null,
      "properties" : null,
      "alternate" : null
    }, {
      "href" : "https://i2.wp.com/img.abctruyen.xyz/uploads/19268/chuong-10/8.jpg",
      "type" : "image/jpeg",
      "bitrate" : 0,
      "duration" : 0,
      "title" : null,
      "properties" : null,
      "alternate" : null
    } ]
  }, {
    "href" : "https://bitbucket.org/wp-tsvhcomic29/comic_storage_two19/raw/master/IMAGE/IMAGE_0a47bd719caa874504c64c192d6dae91_f451f913d5303770df71e77caa48c886_5441f75f918584a721a574ab28910307.jpg",
    "type" : "image/jpeg",
    "bitrate" : 0,
    "duration" : 0,
    "title" : null,
    "properties" : null,
    "alternate" : [ {
      "href" : "https://img.abctruyen.xyz/uploads/19268/chuong-10/9.jpg",
      "type" : "image/jpeg",
      "bitrate" : 0,
      "duration" : 0,
      "title" : null,
      "properties" : null,
      "alternate" : null
    }, {
      "href" : "https://i2.wp.com/img.abctruyen.xyz/uploads/19268/chuong-10/9.jpg",
      "type" : "image/jpeg",
      "bitrate" : 0,
      "duration" : 0,
      "title" : null,
      "properties" : null,
      "alternate" : null
    } ]
  }, {
    "href" : "https://bitbucket.org/wp-tsvhcomic29/comic_storage_two19/raw/master/IMAGE/IMAGE_0a47bd719caa874504c64c192d6dae91_f451f913d5303770df71e77caa48c886_073ab453ae604ab8a8e7a56a59a3c256.jpg",
    "type" : "image/jpeg",
    "bitrate" : 0,
    "duration" : 0,
    "title" : null,
    "properties" : null,
    "alternate" : [ {
      "href" : "https://img.abctruyen.xyz/uploads/19268/chuong-10/10.jpg",
      "type" : "image/jpeg",
      "bitrate" : 0,
      "duration" : 0,
      "title" : null,
      "properties" : null,
      "alternate" : null
    }, {
      "href" : "https://i2.wp.com/img.abctruyen.xyz/uploads/19268/chuong-10/10.jpg",
      "type" : "image/jpeg",
      "bitrate" : 0,
      "duration" : 0,
      "title" : null,
      "properties" : null,
      "alternate" : null
    } ]
  }, {
    "href" : "https://bitbucket.org/wp-tsvhcomic29/comic_storage_two19/raw/master/IMAGE/IMAGE_0a47bd719caa874504c64c192d6dae91_f451f913d5303770df71e77caa48c886_dfa20f3ad3165275345b28943f3f5c0f.jpg",
    "type" : "image/jpeg",
    "bitrate" : 0,
    "duration" : 0,
    "title" : null,
    "properties" : null,
    "alternate" : [ {
      "href" : "https://img.abctruyen.xyz/uploads/19268/chuong-10/11.jpg",
      "type" : "image/jpeg",
      "bitrate" : 0,
      "duration" : 0,
      "title" : null,
      "properties" : null,
      "alternate" : null
    }, {
      "href" : "https://i2.wp.com/img.abctruyen.xyz/uploads/19268/chuong-10/11.jpg",
      "type" : "image/jpeg",
      "bitrate" : 0,
      "duration" : 0,
      "title" : null,
      "properties" : null,
      "alternate" : null
    } ]
  }, {
    "href" : "https://bitbucket.org/wp-tsvhcomic29/comic_storage_two19/raw/master/IMAGE/IMAGE_0a47bd719caa874504c64c192d6dae91_f451f913d5303770df71e77caa48c886_6808cdc9e90510bf92e1a00b8d049140.jpg",
    "type" : "image/jpeg",
    "bitrate" : 0,
    "duration" : 0,
    "title" : null,
    "properties" : null,
    "alternate" : [ {
      "href" : "https://img.abctruyen.xyz/uploads/19268/chuong-10/12.jpg",
      "type" : "image/jpeg",
      "bitrate" : 0,
      "duration" : 0,
      "title" : null,
      "properties" : null,
      "alternate" : null
    }, {
      "href" : "https://i2.wp.com/img.abctruyen.xyz/uploads/19268/chuong-10/12.jpg",
      "type" : "image/jpeg",
      "bitrate" : 0,
      "duration" : 0,
      "title" : null,
      "properties" : null,
      "alternate" : null
    } ]
  }, {
    "href" : "https://bitbucket.org/wp-tsvhcomic29/comic_storage_two19/raw/master/IMAGE/IMAGE_0a47bd719caa874504c64c192d6dae91_f451f913d5303770df71e77caa48c886_bcefb70c2797009fedb3aa797cf8fafd.jpg",
    "type" : "image/jpeg",
    "bitrate" : 0,
    "duration" : 0,
    "title" : null,
    "properties" : null,
    "alternate" : [ {
      "href" : "https://img.abctruyen.xyz/uploads/19268/chuong-10/13.jpg",
      "type" : "image/jpeg",
      "bitrate" : 0,
      "duration" : 0,
      "title" : null,
      "properties" : null,
      "alternate" : null
    }, {
      "href" : "https://i2.wp.com/img.abctruyen.xyz/uploads/19268/chuong-10/13.jpg",
      "type" : "image/jpeg",
      "bitrate" : 0,
      "duration" : 0,
      "title" : null,
      "properties" : null,
      "alternate" : null
    } ]
  }, {
    "href" : "https://bitbucket.org/wp-tsvhcomic29/comic_storage_two19/raw/master/IMAGE/IMAGE_0a47bd719caa874504c64c192d6dae91_f451f913d5303770df71e77caa48c886_a077e1bbdf938db19e0c3e1ddcce9b5b.jpg",
    "type" : "image/jpeg",
    "bitrate" : 0,
    "duration" : 0,
    "title" : null,
    "properties" : null,
    "alternate" : [ {
      "href" : "https://img.abctruyen.xyz/uploads/19268/chuong-10/14.jpg",
      "type" : "image/jpeg",
      "bitrate" : 0,
      "duration" : 0,
      "title" : null,
      "properties" : null,
      "alternate" : null
    }, {
      "href" : "https://i2.wp.com/img.abctruyen.xyz/uploads/19268/chuong-10/14.jpg",
      "type" : "image/jpeg",
      "bitrate" : 0,
      "duration" : 0,
      "title" : null,
      "properties" : null,
      "alternate" : null
    } ]
  }, {
    "href" : "https://bitbucket.org/wp-tsvhcomic29/comic_storage_two19/raw/master/IMAGE/IMAGE_0a47bd719caa874504c64c192d6dae91_f451f913d5303770df71e77caa48c886_73764558b1b5b41893d5d70c7985660b.jpg",
    "type" : "image/jpeg",
    "bitrate" : 0,
    "duration" : 0,
    "title" : null,
    "properties" : null,
    "alternate" : [ {
      "href" : "https://img.abctruyen.xyz/uploads/19268/chuong-10/15.jpg",
      "type" : "image/jpeg",
      "bitrate" : 0,
      "duration" : 0,
      "title" : null,
      "properties" : null,
      "alternate" : null
    }, {
      "href" : "https://i2.wp.com/img.abctruyen.xyz/uploads/19268/chuong-10/15.jpg",
      "type" : "image/jpeg",
      "bitrate" : 0,
      "duration" : 0,
      "title" : null,
      "properties" : null,
      "alternate" : null
    } ]
  }, {
    "href" : "https://bitbucket.org/wp-tsvhcomic29/comic_storage_two19/raw/master/IMAGE/IMAGE_0a47bd719caa874504c64c192d6dae91_f451f913d5303770df71e77caa48c886_46254d1b868ca4f5c4710cddafa26842.jpg",
    "type" : "image/jpeg",
    "bitrate" : 0,
    "duration" : 0,
    "title" : null,
    "properties" : null,
    "alternate" : [ {
      "href" : "https://img.abctruyen.xyz/uploads/19268/chuong-10/16.jpg",
      "type" : "image/jpeg",
      "bitrate" : 0,
      "duration" : 0,
      "title" : null,
      "properties" : null,
      "alternate" : null
    }, {
      "href" : "https://i2.wp.com/img.abctruyen.xyz/uploads/19268/chuong-10/16.jpg",
      "type" : "image/jpeg",
      "bitrate" : 0,
      "duration" : 0,
      "title" : null,
      "properties" : null,
      "alternate" : null
    } ]
  }, {
    "href" : "https://bitbucket.org/wp-tsvhcomic29/comic_storage_two19/raw/master/IMAGE/IMAGE_0a47bd719caa874504c64c192d6dae91_f451f913d5303770df71e77caa48c886_d67cf1c05bd6a952c53fe39cf3012306.jpg",
    "type" : "image/jpeg",
    "bitrate" : 0,
    "duration" : 0,
    "title" : null,
    "properties" : null,
    "alternate" : [ {
      "href" : "https://img.abctruyen.xyz/uploads/19268/chuong-10/17.jpg",
      "type" : "image/jpeg",
      "bitrate" : 0,
      "duration" : 0,
      "title" : null,
      "properties" : null,
      "alternate" : null
    }, {
      "href" : "https://i2.wp.com/img.abctruyen.xyz/uploads/19268/chuong-10/17.jpg",
      "type" : "image/jpeg",
      "bitrate" : 0,
      "duration" : 0,
      "title" : null,
      "properties" : null,
      "alternate" : null
    } ]
  }, {
    "href" : "https://bitbucket.org/wp-tsvhcomic29/comic_storage_two19/raw/master/IMAGE/IMAGE_0a47bd719caa874504c64c192d6dae91_f451f913d5303770df71e77caa48c886_8696375f6785c5cc74d4f612fa35920b.jpg",
    "type" : "image/jpeg",
    "bitrate" : 0,
    "duration" : 0,
    "title" : null,
    "properties" : null,
    "alternate" : [ {
      "href" : "https://img.abctruyen.xyz/uploads/19268/chuong-10/18.jpg",
      "type" : "image/jpeg",
      "bitrate" : 0,
      "duration" : 0,
      "title" : null,
      "properties" : null,
      "alternate" : null
    }, {
      "href" : "https://i2.wp.com/img.abctruyen.xyz/uploads/19268/chuong-10/18.jpg",
      "type" : "image/jpeg",
      "bitrate" : 0,
      "duration" : 0,
      "title" : null,
      "properties" : null,
      "alternate" : null
    } ]
  }, {
    "href" : "https://bitbucket.org/wp-tsvhcomic29/comic_storage_two19/raw/master/IMAGE/IMAGE_0a47bd719caa874504c64c192d6dae91_f451f913d5303770df71e77caa48c886_a33e06c752bfa594ae6d6cc69817b7ef.jpg",
    "type" : "image/jpeg",
    "bitrate" : 0,
    "duration" : 0,
    "title" : null,
    "properties" : null,
    "alternate" : [ {
      "href" : "https://img.abctruyen.xyz/uploads/19268/chuong-10/19.jpg",
      "type" : "image/jpeg",
      "bitrate" : 0,
      "duration" : 0,
      "title" : null,
      "properties" : null,
      "alternate" : null
    }, {
      "href" : "https://i2.wp.com/img.abctruyen.xyz/uploads/19268/chuong-10/19.jpg",
      "type" : "image/jpeg",
      "bitrate" : 0,
      "duration" : 0,
      "title" : null,
      "properties" : null,
      "alternate" : null
    } ]
  }, {
    "href" : "https://bitbucket.org/wp-tsvhcomic29/comic_storage_two19/raw/master/IMAGE/IMAGE_0a47bd719caa874504c64c192d6dae91_f451f913d5303770df71e77caa48c886_2b61d04f4efc6345c0a49f14f39b4db0.jpg",
    "type" : "image/jpeg",
    "bitrate" : 0,
    "duration" : 0,
    "title" : null,
    "properties" : null,
    "alternate" : [ {
      "href" : "https://img.abctruyen.xyz/uploads/19268/chuong-10/20.jpg",
      "type" : "image/jpeg",
      "bitrate" : 0,
      "duration" : 0,
      "title" : null,
      "properties" : null,
      "alternate" : null
    }, {
      "href" : "https://i2.wp.com/img.abctruyen.xyz/uploads/19268/chuong-10/20.jpg",
      "type" : "image/jpeg",
      "bitrate" : 0,
      "duration" : 0,
      "title" : null,
      "properties" : null,
      "alternate" : null
    } ]
  }, {
    "href" : "https://bitbucket.org/wp-tsvhcomic29/comic_storage_two19/raw/master/IMAGE/IMAGE_0a47bd719caa874504c64c192d6dae91_f451f913d5303770df71e77caa48c886_aa3cd1acff73935c64008b7cff0e6f46.jpg",
    "type" : "image/jpeg",
    "bitrate" : 0,
    "duration" : 0,
    "title" : null,
    "properties" : null,
    "alternate" : [ {
      "href" : "https://img.abctruyen.xyz/uploads/19268/chuong-10/21.jpg",
      "type" : "image/jpeg",
      "bitrate" : 0,
      "duration" : 0,
      "title" : null,
      "properties" : null,
      "alternate" : null
    }, {
      "href" : "https://i2.wp.com/img.abctruyen.xyz/uploads/19268/chuong-10/21.jpg",
      "type" : "image/jpeg",
      "bitrate" : 0,
      "duration" : 0,
      "title" : null,
      "properties" : null,
      "alternate" : null
    } ]
  }, {
    "href" : "https://bitbucket.org/wp-tsvhcomic29/comic_storage_two19/raw/master/IMAGE/IMAGE_0a47bd719caa874504c64c192d6dae91_f451f913d5303770df71e77caa48c886_b1d19f52a5d93f173dc51da0bc0827e6.jpg",
    "type" : "image/jpeg",
    "bitrate" : 0,
    "duration" : 0,
    "title" : null,
    "properties" : null,
    "alternate" : [ {
      "href" : "https://img.abctruyen.xyz/uploads/19268/chuong-10/22.jpg",
      "type" : "image/jpeg",
      "bitrate" : 0,
      "duration" : 0,
      "title" : null,
      "properties" : null,
      "alternate" : null
    }, {
      "href" : "https://i2.wp.com/img.abctruyen.xyz/uploads/19268/chuong-10/22.jpg",
      "type" : "image/jpeg",
      "bitrate" : 0,
      "duration" : 0,
      "title" : null,
      "properties" : null,
      "alternate" : null
    } ]
  }, {
    "href" : "https://bitbucket.org/wp-tsvhcomic29/comic_storage_two19/raw/master/IMAGE/IMAGE_0a47bd719caa874504c64c192d6dae91_f451f913d5303770df71e77caa48c886_1a3ff4c2e97b8c5f15b50e2280428519.jpg",
    "type" : "image/jpeg",
    "bitrate" : 0,
    "duration" : 0,
    "title" : null,
    "properties" : null,
    "alternate" : [ {
      "href" : "https://img.abctruyen.xyz/uploads/19268/chuong-10/23.jpg",
      "type" : "image/jpeg",
      "bitrate" : 0,
      "duration" : 0,
      "title" : null,
      "properties" : null,
      "alternate" : null
    }, {
      "href" : "https://i2.wp.com/img.abctruyen.xyz/uploads/19268/chuong-10/23.jpg",
      "type" : "image/jpeg",
      "bitrate" : 0,
      "duration" : 0,
      "title" : null,
      "properties" : null,
      "alternate" : null
    } ]
  }, {
    "href" : "https://bitbucket.org/wp-tsvhcomic29/comic_storage_two19/raw/master/IMAGE/IMAGE_0a47bd719caa874504c64c192d6dae91_f451f913d5303770df71e77caa48c886_c1440554232f6d5ce24239752f508f31.jpg",
    "type" : "image/jpeg",
    "bitrate" : 0,
    "duration" : 0,
    "title" : null,
    "properties" : null,
    "alternate" : [ {
      "href" : "https://img.abctruyen.xyz/uploads/19268/chuong-10/24.jpg",
      "type" : "image/jpeg",
      "bitrate" : 0,
      "duration" : 0,
      "title" : null,
      "properties" : null,
      "alternate" : null
    }, {
      "href" : "https://i2.wp.com/img.abctruyen.xyz/uploads/19268/chuong-10/24.jpg",
      "type" : "image/jpeg",
      "bitrate" : 0,
      "duration" : 0,
      "title" : null,
      "properties" : null,
      "alternate" : null
    } ]
  }, {
    "href" : "https://bitbucket.org/wp-tsvhcomic29/comic_storage_two19/raw/master/IMAGE/IMAGE_0a47bd719caa874504c64c192d6dae91_f451f913d5303770df71e77caa48c886_07f639ccbcb266ffd09da2c6469c2b82.jpg",
    "type" : "image/jpeg",
    "bitrate" : 0,
    "duration" : 0,
    "title" : null,
    "properties" : null,
    "alternate" : [ {
      "href" : "https://img.abctruyen.xyz/uploads/19268/chuong-10/25.jpg",
      "type" : "image/jpeg",
      "bitrate" : 0,
      "duration" : 0,
      "title" : null,
      "properties" : null,
      "alternate" : null
    }, {
      "href" : "https://i2.wp.com/img.abctruyen.xyz/uploads/19268/chuong-10/25.jpg",
      "type" : "image/jpeg",
      "bitrate" : 0,
      "duration" : 0,
      "title" : null,
      "properties" : null,
      "alternate" : null
    } ]
  }, {
    "href" : "https://bitbucket.org/wp-tsvhcomic29/comic_storage_two19/raw/master/IMAGE/IMAGE_0a47bd719caa874504c64c192d6dae91_f451f913d5303770df71e77caa48c886_ce6e79f485017469fa9fd23c08c42e97.jpg",
    "type" : "image/jpeg",
    "bitrate" : 0,
    "duration" : 0,
    "title" : null,
    "properties" : null,
    "alternate" : [ {
      "href" : "https://img.abctruyen.xyz/uploads/19268/chuong-10/26.jpg",
      "type" : "image/jpeg",
      "bitrate" : 0,
      "duration" : 0,
      "title" : null,
      "properties" : null,
      "alternate" : null
    }, {
      "href" : "https://i2.wp.com/img.abctruyen.xyz/uploads/19268/chuong-10/26.jpg",
      "type" : "image/jpeg",
      "bitrate" : 0,
      "duration" : 0,
      "title" : null,
      "properties" : null,
      "alternate" : null
    } ]
  }, {
    "href" : "https://bitbucket.org/wp-tsvhcomic29/comic_storage_two19/raw/master/IMAGE/IMAGE_0a47bd719caa874504c64c192d6dae91_f451f913d5303770df71e77caa48c886_a5f2a2788ec797eda4f5f76b339d3f85.jpg",
    "type" : "image/jpeg",
    "bitrate" : 0,
    "duration" : 0,
    "title" : null,
    "properties" : null,
    "alternate" : [ {
      "href" : "https://img.abctruyen.xyz/uploads/19268/chuong-10/27.jpg",
      "type" : "image/jpeg",
      "bitrate" : 0,
      "duration" : 0,
      "title" : null,
      "properties" : null,
      "alternate" : null
    }, {
      "href" : "https://i2.wp.com/img.abctruyen.xyz/uploads/19268/chuong-10/27.jpg",
      "type" : "image/jpeg",
      "bitrate" : 0,
      "duration" : 0,
      "title" : null,
      "properties" : null,
      "alternate" : null
    } ]
  }, {
    "href" : "https://bitbucket.org/wp-tsvhcomic29/comic_storage_two19/raw/master/IMAGE/IMAGE_0a47bd719caa874504c64c192d6dae91_f451f913d5303770df71e77caa48c886_2429bccbb40aa1624a1f51ff193e2402.jpg",
    "type" : "image/jpeg",
    "bitrate" : 0,
    "duration" : 0,
    "title" : null,
    "properties" : null,
    "alternate" : [ {
      "href" : "https://img.abctruyen.xyz/uploads/19268/chuong-10/28.jpg",
      "type" : "image/jpeg",
      "bitrate" : 0,
      "duration" : 0,
      "title" : null,
      "properties" : null,
      "alternate" : null
    }, {
      "href" : "https://i2.wp.com/img.abctruyen.xyz/uploads/19268/chuong-10/28.jpg",
      "type" : "image/jpeg",
      "bitrate" : 0,
      "duration" : 0,
      "title" : null,
      "properties" : null,
      "alternate" : null
    } ]
  }, {
    "href" : "https://bitbucket.org/wp-tsvhcomic29/comic_storage_two19/raw/master/IMAGE/IMAGE_0a47bd719caa874504c64c192d6dae91_f451f913d5303770df71e77caa48c886_f18fe19e51a606a12debc1a72b59d481.jpg",
    "type" : "image/jpeg",
    "bitrate" : 0,
    "duration" : 0,
    "title" : null,
    "properties" : null,
    "alternate" : [ {
      "href" : "https://img.abctruyen.xyz/uploads/19268/chuong-10/29.jpg",
      "type" : "image/jpeg",
      "bitrate" : 0,
      "duration" : 0,
      "title" : null,
      "properties" : null,
      "alternate" : null
    }, {
      "href" : "https://i2.wp.com/img.abctruyen.xyz/uploads/19268/chuong-10/29.jpg",
      "type" : "image/jpeg",
      "bitrate" : 0,
      "duration" : 0,
      "title" : null,
      "properties" : null,
      "alternate" : null
    } ]
  }, {
    "href" : "https://bitbucket.org/wp-tsvhcomic29/comic_storage_two19/raw/master/IMAGE/IMAGE_0a47bd719caa874504c64c192d6dae91_f451f913d5303770df71e77caa48c886_e20be276e20a5c8dee0904ece269ada7.jpg",
    "type" : "image/jpeg",
    "bitrate" : 0,
    "duration" : 0,
    "title" : null,
    "properties" : null,
    "alternate" : [ {
      "href" : "https://img.abctruyen.xyz/uploads/19268/chuong-10/30.jpg",
      "type" : "image/jpeg",
      "bitrate" : 0,
      "duration" : 0,
      "title" : null,
      "properties" : null,
      "alternate" : null
    }, {
      "href" : "https://i2.wp.com/img.abctruyen.xyz/uploads/19268/chuong-10/30.jpg",
      "type" : "image/jpeg",
      "bitrate" : 0,
      "duration" : 0,
      "title" : null,
      "properties" : null,
      "alternate" : null
    } ]
  }, {
    "href" : "https://bitbucket.org/wp-tsvhcomic29/comic_storage_two19/raw/master/IMAGE/IMAGE_0a47bd719caa874504c64c192d6dae91_f451f913d5303770df71e77caa48c886_79660a9ac8caf5bcabdc74faaf7202a0.jpg",
    "type" : "image/jpeg",
    "bitrate" : 0,
    "duration" : 0,
    "title" : null,
    "properties" : null,
    "alternate" : [ {
      "href" : "https://img.abctruyen.xyz/uploads/19268/chuong-10/31.jpg",
      "type" : "image/jpeg",
      "bitrate" : 0,
      "duration" : 0,
      "title" : null,
      "properties" : null,
      "alternate" : null
    }, {
      "href" : "https://i2.wp.com/img.abctruyen.xyz/uploads/19268/chuong-10/31.jpg",
      "type" : "image/jpeg",
      "bitrate" : 0,
      "duration" : 0,
      "title" : null,
      "properties" : null,
      "alternate" : null
    } ]
  }, {
    "href" : "https://bitbucket.org/wp-tsvhcomic29/comic_storage_two19/raw/master/IMAGE/IMAGE_0a47bd719caa874504c64c192d6dae91_f451f913d5303770df71e77caa48c886_6844c5ad0255a4b3542b0cc1cd09bfb1.jpg",
    "type" : "image/jpeg",
    "bitrate" : 0,
    "duration" : 0,
    "title" : null,
    "properties" : null,
    "alternate" : [ {
      "href" : "https://img.abctruyen.xyz/uploads/19268/chuong-10/32.jpg",
      "type" : "image/jpeg",
      "bitrate" : 0,
      "duration" : 0,
      "title" : null,
      "properties" : null,
      "alternate" : null
    }, {
      "href" : "https://i2.wp.com/img.abctruyen.xyz/uploads/19268/chuong-10/32.jpg",
      "type" : "image/jpeg",
      "bitrate" : 0,
      "duration" : 0,
      "title" : null,
      "properties" : null,
      "alternate" : null
    } ]
  }, {
    "href" : "https://bitbucket.org/wp-tsvhcomic29/comic_storage_two19/raw/master/IMAGE/IMAGE_0a47bd719caa874504c64c192d6dae91_f451f913d5303770df71e77caa48c886_a74561d388fa634f1388182375178baa.jpg",
    "type" : "image/jpeg",
    "bitrate" : 0,
    "duration" : 0,
    "title" : null,
    "properties" : null,
    "alternate" : [ {
      "href" : "https://img.abctruyen.xyz/uploads/19268/chuong-10/33.jpg",
      "type" : "image/jpeg",
      "bitrate" : 0,
      "duration" : 0,
      "title" : null,
      "properties" : null,
      "alternate" : null
    }, {
      "href" : "https://i2.wp.com/img.abctruyen.xyz/uploads/19268/chuong-10/33.jpg",
      "type" : "image/jpeg",
      "bitrate" : 0,
      "duration" : 0,
      "title" : null,
      "properties" : null,
      "alternate" : null
    } ]
  }, {
    "href" : "https://bitbucket.org/wp-tsvhcomic29/comic_storage_two19/raw/master/IMAGE/IMAGE_0a47bd719caa874504c64c192d6dae91_f451f913d5303770df71e77caa48c886_23a8c68ec633438e8229872ce67c5e5a.jpg",
    "type" : "image/jpeg",
    "bitrate" : 0,
    "duration" : 0,
    "title" : null,
    "properties" : null,
    "alternate" : [ {
      "href" : "https://img.abctruyen.xyz/uploads/19268/chuong-10/34.jpg",
      "type" : "image/jpeg",
      "bitrate" : 0,
      "duration" : 0,
      "title" : null,
      "properties" : null,
      "alternate" : null
    }, {
      "href" : "https://i2.wp.com/img.abctruyen.xyz/uploads/19268/chuong-10/34.jpg",
      "type" : "image/jpeg",
      "bitrate" : 0,
      "duration" : 0,
      "title" : null,
      "properties" : null,
      "alternate" : null
    } ]
  }, {
    "href" : "https://bitbucket.org/wp-tsvhcomic29/comic_storage_two19/raw/master/IMAGE/IMAGE_0a47bd719caa874504c64c192d6dae91_f451f913d5303770df71e77caa48c886_c487206b354a8656197e8beee90b144f.jpg",
    "type" : "image/jpeg",
    "bitrate" : 0,
    "duration" : 0,
    "title" : null,
    "properties" : null,
    "alternate" : [ {
      "href" : "https://img.abctruyen.xyz/uploads/19268/chuong-10/35.jpg",
      "type" : "image/jpeg",
      "bitrate" : 0,
      "duration" : 0,
      "title" : null,
      "properties" : null,
      "alternate" : null
    }, {
      "href" : "https://i2.wp.com/img.abctruyen.xyz/uploads/19268/chuong-10/35.jpg",
      "type" : "image/jpeg",
      "bitrate" : 0,
      "duration" : 0,
      "title" : null,
      "properties" : null,
      "alternate" : null
    } ]
  }, {
    "href" : "https://bitbucket.org/wp-tsvhcomic29/comic_storage_two19/raw/master/IMAGE/IMAGE_0a47bd719caa874504c64c192d6dae91_f451f913d5303770df71e77caa48c886_625c86f2804a77331df6a5059005eff0.jpg",
    "type" : "image/jpeg",
    "bitrate" : 0,
    "duration" : 0,
    "title" : null,
    "properties" : null,
    "alternate" : [ {
      "href" : "https://img.abctruyen.xyz/uploads/19268/chuong-10/36.jpg",
      "type" : "image/jpeg",
      "bitrate" : 0,
      "duration" : 0,
      "title" : null,
      "properties" : null,
      "alternate" : null
    }, {
      "href" : "https://i2.wp.com/img.abctruyen.xyz/uploads/19268/chuong-10/36.jpg",
      "type" : "image/jpeg",
      "bitrate" : 0,
      "duration" : 0,
      "title" : null,
      "properties" : null,
      "alternate" : null
    } ]
  }, {
    "href" : "https://bitbucket.org/wp-tsvhcomic29/comic_storage_two19/raw/master/IMAGE/IMAGE_0a47bd719caa874504c64c192d6dae91_f451f913d5303770df71e77caa48c886_e46778b894f353cfe7007b4d7f56e024.jpg",
    "type" : "image/jpeg",
    "bitrate" : 0,
    "duration" : 0,
    "title" : null,
    "properties" : null,
    "alternate" : [ {
      "href" : "https://img.abctruyen.xyz/uploads/19268/chuong-10/37.jpg",
      "type" : "image/jpeg",
      "bitrate" : 0,
      "duration" : 0,
      "title" : null,
      "properties" : null,
      "alternate" : null
    }, {
      "href" : "https://i2.wp.com/img.abctruyen.xyz/uploads/19268/chuong-10/37.jpg",
      "type" : "image/jpeg",
      "bitrate" : 0,
      "duration" : 0,
      "title" : null,
      "properties" : null,
      "alternate" : null
    } ]
  }, {
    "href" : "https://bitbucket.org/wp-tsvhcomic29/comic_storage_two19/raw/master/IMAGE/IMAGE_0a47bd719caa874504c64c192d6dae91_f451f913d5303770df71e77caa48c886_8724dd457ac0f96a67df9b699c57b0fc.jpg",
    "type" : "image/jpeg",
    "bitrate" : 0,
    "duration" : 0,
    "title" : null,
    "properties" : null,
    "alternate" : [ {
      "href" : "https://img.abctruyen.xyz/uploads/19268/chuong-10/38.jpg",
      "type" : "image/jpeg",
      "bitrate" : 0,
      "duration" : 0,
      "title" : null,
      "properties" : null,
      "alternate" : null
    }, {
      "href" : "https://i2.wp.com/img.abctruyen.xyz/uploads/19268/chuong-10/38.jpg",
      "type" : "image/jpeg",
      "bitrate" : 0,
      "duration" : 0,
      "title" : null,
      "properties" : null,
      "alternate" : null
    } ]
  }, {
    "href" : "https://bitbucket.org/wp-tsvhcomic29/comic_storage_two19/raw/master/IMAGE/IMAGE_0a47bd719caa874504c64c192d6dae91_f451f913d5303770df71e77caa48c886_e139e9a78d0887c2e6de3f08f27c8972.jpg",
    "type" : "image/jpeg",
    "bitrate" : 0,
    "duration" : 0,
    "title" : null,
    "properties" : null,
    "alternate" : [ {
      "href" : "https://img.abctruyen.xyz/uploads/19268/chuong-10/39.jpg",
      "type" : "image/jpeg",
      "bitrate" : 0,
      "duration" : 0,
      "title" : null,
      "properties" : null,
      "alternate" : null
    }, {
      "href" : "https://i2.wp.com/img.abctruyen.xyz/uploads/19268/chuong-10/39.jpg",
      "type" : "image/jpeg",
      "bitrate" : 0,
      "duration" : 0,
      "title" : null,
      "properties" : null,
      "alternate" : null
    } ]
  }, {
    "href" : "https://bitbucket.org/wp-tsvhcomic29/comic_storage_two19/raw/master/IMAGE/IMAGE_0a47bd719caa874504c64c192d6dae91_f451f913d5303770df71e77caa48c886_bf8fdb228fa782c6f85589e17c5aabc5.jpg",
    "type" : "image/jpeg",
    "bitrate" : 0,
    "duration" : 0,
    "title" : null,
    "properties" : null,
    "alternate" : [ {
      "href" : "https://img.abctruyen.xyz/uploads/19268/chuong-10/40.jpg",
      "type" : "image/jpeg",
      "bitrate" : 0,
      "duration" : 0,
      "title" : null,
      "properties" : null,
      "alternate" : null
    }, {
      "href" : "https://i2.wp.com/img.abctruyen.xyz/uploads/19268/chuong-10/40.jpg",
      "type" : "image/jpeg",
      "bitrate" : 0,
      "duration" : 0,
      "title" : null,
      "properties" : null,
      "alternate" : null
    } ]
  }, {
    "href" : "https://bitbucket.org/wp-tsvhcomic29/comic_storage_two19/raw/master/IMAGE/IMAGE_0a47bd719caa874504c64c192d6dae91_f451f913d5303770df71e77caa48c886_a31dff502d56f8fc9dcd4d0fc8715e7d.jpg",
    "type" : "image/jpeg",
    "bitrate" : 0,
    "duration" : 0,
    "title" : null,
    "properties" : null,
    "alternate" : [ {
      "href" : "https://img.abctruyen.xyz/uploads/19268/chuong-10/41.jpg",
      "type" : "image/jpeg",
      "bitrate" : 0,
      "duration" : 0,
      "title" : null,
      "properties" : null,
      "alternate" : null
    }, {
      "href" : "https://i2.wp.com/img.abctruyen.xyz/uploads/19268/chuong-10/41.jpg",
      "type" : "image/jpeg",
      "bitrate" : 0,
      "duration" : 0,
      "title" : null,
      "properties" : null,
      "alternate" : null
    } ]
  }, {
    "href" : "https://bitbucket.org/wp-tsvhcomic29/comic_storage_two19/raw/master/IMAGE/IMAGE_0a47bd719caa874504c64c192d6dae91_f451f913d5303770df71e77caa48c886_1eca053fee0506c1eb9cf602cdf57f27.jpg",
    "type" : "image/jpeg",
    "bitrate" : 0,
    "duration" : 0,
    "title" : null,
    "properties" : null,
    "alternate" : [ {
      "href" : "https://img.abctruyen.xyz/uploads/19268/chuong-10/42.jpg",
      "type" : "image/jpeg",
      "bitrate" : 0,
      "duration" : 0,
      "title" : null,
      "properties" : null,
      "alternate" : null
    }, {
      "href" : "https://i2.wp.com/img.abctruyen.xyz/uploads/19268/chuong-10/42.jpg",
      "type" : "image/jpeg",
      "bitrate" : 0,
      "duration" : 0,
      "title" : null,
      "properties" : null,
      "alternate" : null
    } ]
  }, {
    "href" : "https://bitbucket.org/wp-tsvhcomic29/comic_storage_two19/raw/master/IMAGE/IMAGE_0a47bd719caa874504c64c192d6dae91_f451f913d5303770df71e77caa48c886_52b0fb269976a3ac22f3b83f83b528be.jpg",
    "type" : "image/jpeg",
    "bitrate" : 0,
    "duration" : 0,
    "title" : null,
    "properties" : null,
    "alternate" : [ {
      "href" : "https://img.abctruyen.xyz/uploads/19268/chuong-10/43.jpg",
      "type" : "image/jpeg",
      "bitrate" : 0,
      "duration" : 0,
      "title" : null,
      "properties" : null,
      "alternate" : null
    }, {
      "href" : "https://i2.wp.com/img.abctruyen.xyz/uploads/19268/chuong-10/43.jpg",
      "type" : "image/jpeg",
      "bitrate" : 0,
      "duration" : 0,
      "title" : null,
      "properties" : null,
      "alternate" : null
    } ]
  }, {
    "href" : "https://bitbucket.org/wp-tsvhcomic29/comic_storage_two19/raw/master/IMAGE/IMAGE_0a47bd719caa874504c64c192d6dae91_f451f913d5303770df71e77caa48c886_97cad3c3b3d6282570d6579abf912267.jpg",
    "type" : "image/jpeg",
    "bitrate" : 0,
    "duration" : 0,
    "title" : null,
    "properties" : null,
    "alternate" : [ {
      "href" : "https://img.abctruyen.xyz/uploads/19268/chuong-10/44.jpg",
      "type" : "image/jpeg",
      "bitrate" : 0,
      "duration" : 0,
      "title" : null,
      "properties" : null,
      "alternate" : null
    }, {
      "href" : "https://i2.wp.com/img.abctruyen.xyz/uploads/19268/chuong-10/44.jpg",
      "type" : "image/jpeg",
      "bitrate" : 0,
      "duration" : 0,
      "title" : null,
      "properties" : null,
      "alternate" : null
    } ]
  }, {
    "href" : "https://bitbucket.org/wp-tsvhcomic29/comic_storage_two19/raw/master/IMAGE/IMAGE_0a47bd719caa874504c64c192d6dae91_f451f913d5303770df71e77caa48c886_49dfa0c4ed98d9f88b7531f60ce39770.jpg",
    "type" : "image/jpeg",
    "bitrate" : 0,
    "duration" : 0,
    "title" : null,
    "properties" : null,
    "alternate" : [ {
      "href" : "https://img.abctruyen.xyz/uploads/19268/chuong-10/45.jpg",
      "type" : "image/jpeg",
      "bitrate" : 0,
      "duration" : 0,
      "title" : null,
      "properties" : null,
      "alternate" : null
    }, {
      "href" : "https://i2.wp.com/img.abctruyen.xyz/uploads/19268/chuong-10/45.jpg",
      "type" : "image/jpeg",
      "bitrate" : 0,
      "duration" : 0,
      "title" : null,
      "properties" : null,
      "alternate" : null
    } ]
  } ],
  "toc" : null,
  "@context" : "https://readium.org/webpub-manifest/context.jsonld"
}